elasticsearch7_dsl/__init__.py
elasticsearch7_dsl/aggs.py
elasticsearch7_dsl/analysis.py
elasticsearch7_dsl/connections.py
elasticsearch7_dsl/document.py
elasticsearch7_dsl/exceptions.py
elasticsearch7_dsl/faceted_search.py
elasticsearch7_dsl/field.py
elasticsearch7_dsl/function.py
elasticsearch7_dsl/index.py
elasticsearch7_dsl/mapping.py
elasticsearch7_dsl/query.py
elasticsearch7_dsl/search.py
elasticsearch7_dsl/serializer.py
elasticsearch7_dsl/update_by_query.py
elasticsearch7_dsl/utils.py
elasticsearch7_dsl/wrappers.py
elasticsearch7_dsl/response/__init__.py
elasticsearch7_dsl/response/aggs.py
elasticsearch7_dsl/response/hit.py
elasticsearch7_dsl-7.3.0.post1.dist-info/AUTHORS
elasticsearch7_dsl-7.3.0.post1.dist-info/LICENSE
elasticsearch7_dsl-7.3.0.post1.dist-info/METADATA
elasticsearch7_dsl-7.3.0.post1.dist-info/WHEEL
elasticsearch7_dsl-7.3.0.post1.dist-info/top_level.txt
elasticsearch7_dsl-7.3.0.post1.dist-info/RECORD
