Metadata-Version: 2.1
Name: elasticsearch7-dsl
Version: 7.3.0.post1
Summary: Python client for Elasticsearch
Home-page: https://github.com/elasticsearch/elasticsearch-dsl-py
Author: Honza Král
Author-email: honza.kral@gmail.com
Maintainer: Seth Michael Larson
Maintainer-email: seth.larson@elastic.co
License: Apache-2.0
Platform: UNKNOWN
Classifier: Development Status :: 4 - Beta
Classifier: License :: OSI Approved :: Apache Software License
Classifier: Intended Audience :: Developers
Classifier: Operating System :: OS Independent
Classifier: Programming Language :: Python
Classifier: Programming Language :: Python :: 2
Classifier: Programming Language :: Python :: 2.7
Classifier: Programming Language :: Python :: 3
Classifier: Programming Language :: Python :: 3.4
Classifier: Programming Language :: Python :: 3.5
Classifier: Programming Language :: Python :: 3.6
Classifier: Programming Language :: Python :: 3.7
Classifier: Programming Language :: Python :: 3.8
Classifier: Programming Language :: Python :: 3.9
Classifier: Programming Language :: Python :: Implementation :: CPython
Classifier: Programming Language :: Python :: Implementation :: PyPy
Requires-Python: >=2.7, !=3.0.*, !=3.1.*, !=3.2.*, !=3.3.*
Requires-Dist: six
Requires-Dist: python-dateutil
Requires-Dist: elasticsearch7 (<8.0.0,>=7.0.0)
Requires-Dist: ipaddress ; python_version < "3.3"
Provides-Extra: develop
Requires-Dist: mock ; extra == 'develop'
Requires-Dist: pytest (>=3.0.0) ; extra == 'develop'
Requires-Dist: pytest-cov ; extra == 'develop'
Requires-Dist: pytest-mock (<3.0.0) ; extra == 'develop'
Requires-Dist: pytz ; extra == 'develop'
Requires-Dist: coverage (<5.0.0) ; extra == 'develop'
Requires-Dist: sphinx ; extra == 'develop'
Requires-Dist: sphinx-rtd-theme ; extra == 'develop'
